<?xml version="1.0" encoding="utf-8" standalone="yes"?><w:document xmlns:o="urn:schemas-microsoft-com:office:office" xmlns:r="http://schemas.openxmlformats.org/officeDocument/2006/relationships" xmlns:v="urn:schemas-microsoft-com:vml" xmlns:w="http://schemas.openxmlformats.org/wordprocessingml/2006/main" xmlns:w10="urn:schemas-microsoft-com:office:word" xmlns:wp="http://schemas.openxmlformats.org/drawingml/2006/wordprocessingDrawing" xmlns:wps="http://schemas.microsoft.com/office/word/2010/wordprocessingShape" xmlns:wpg="http://schemas.microsoft.com/office/word/2010/wordprocessingGroup" xmlns:mc="http://schemas.openxmlformats.org/markup-compatibility/2006" xmlns:wp14="http://schemas.microsoft.com/office/word/2010/wordprocessingDrawing" xmlns:w14="http://schemas.microsoft.com/office/word/2010/wordml" mc:Ignorable="w14 wp14"><w:body><w:p w:rsidP="3DB3F1AF" w14:paraId="53FDABE3" xmlns:wp14="http://schemas.microsoft.com/office/word/2010/wordml" wp14:textId="6B19D258"><w:pPr><w:pStyle w:val="Normal" /><w:bidi w:val="0" /><w:jc w:val="left" /><w:rPr><w:rFonts w:ascii="Times New Roman" w:hAnsi="Times New Roman" w:eastAsia="Times New Roman" w:cs="Times New Roman" /></w:rPr></w:pPr><w:r w:rsidRPr="3DB3F1AF" w:rsidR="3DB3F1AF"><w:rPr><w:rFonts w:ascii="Times New Roman" w:hAnsi="Times New Roman" w:eastAsia="Times New Roman" w:cs="Times New Roman" /></w:rPr><w:t xml:space="preserve">This is my Word document. </w:t></w:r><w:r w:rsidRPr="3DB3F1AF" w:rsidR="3DB3F1AF"><w:rPr><w:rFonts w:ascii="Times New Roman" w:hAnsi="Times New Roman" w:eastAsia="Times New Roman" w:cs="Times New Roman" /></w:rPr><w:t xml:space="preserve">It has </w:t></w:r><w:r w:rsidRPr="3DB3F1AF" w:rsidR="3DB3F1AF"><w:rPr><w:rFonts w:ascii="Times New Roman" w:hAnsi="Times New Roman" w:eastAsia="Times New Roman" w:cs="Times New Roman" /><w:b w:val="1" /><w:bCs w:val="1" /><w:i w:val="0" /><w:iCs w:val="0" /></w:rPr><w:t xml:space="preserve">bold </w:t></w:r><w:r w:rsidRPr="3DB3F1AF" w:rsidR="3DB3F1AF"><w:rPr><w:rFonts w:ascii="Times New Roman" w:hAnsi="Times New Roman" w:eastAsia="Times New Roman" w:cs="Times New Roman" /></w:rPr><w:t xml:space="preserve">text, </w:t></w:r><w:r w:rsidRPr="3DB3F1AF" w:rsidR="3DB3F1AF"><w:rPr><w:rFonts w:ascii="Times New Roman" w:hAnsi="Times New Roman" w:eastAsia="Times New Roman" w:cs="Times New Roman" /><w:i w:val="1" /><w:iCs w:val="1" /></w:rPr><w:t xml:space="preserve">italics </w:t></w:r><w:r w:rsidRPr="3DB3F1AF" w:rsidR="3DB3F1AF"><w:rPr><w:rFonts w:ascii="Times New Roman" w:hAnsi="Times New Roman" w:eastAsia="Times New Roman" w:cs="Times New Roman" /></w:rPr><w:t>and</w:t></w:r></w:p><w:p w:rsidP="3DB3F1AF" w14:paraId="672A6659" wp14:textId="77777777" xmlns:wp14="http://schemas.microsoft.com/office/word/2010/wordml"><w:pPr><w:pStyle w:val="Normal" /><w:bidi w:val="0" /><w:jc w:val="left" /><w:rPr><w:rFonts w:ascii="Times New Roman" w:hAnsi="Times New Roman" w:eastAsia="Times New Roman" w:cs="Times New Roman" /></w:rPr></w:pPr></w:p><w:p w:rsidP="3DB3F1AF" w14:paraId="1F3047DB" wp14:textId="77777777" xmlns:wp14="http://schemas.microsoft.com/office/word/2010/wordml"><w:pPr><w:pStyle w:val="Normal" /><w:numPr><w:ilvl w:val="0" /><w:numId w:val="1" /></w:numPr><w:bidi w:val="0" /><w:jc w:val="left" /><w:rPr><w:rFonts w:ascii="Times New Roman" w:hAnsi="Times New Roman" w:eastAsia="Times New Roman" w:cs="Times New Roman" /></w:rPr></w:pPr><w:r w:rsidRPr="3DB3F1AF" w:rsidR="3DB3F1AF"><w:rPr><w:rFonts w:ascii="Times New Roman" w:hAnsi="Times New Roman" w:eastAsia="Times New Roman" w:cs="Times New Roman" /></w:rPr><w:t>It</w:t></w:r></w:p><w:p w:rsidP="3DB3F1AF" xmlns:wp14="http://schemas.microsoft.com/office/word/2010/wordml" w14:paraId="0E78156A" wp14:textId="14DA79F7"><w:pPr><w:pStyle w:val="Normal" /><w:numPr><w:ilvl w:val="0" /><w:numId w:val="1" /></w:numPr><w:bidi w:val="0" /><w:jc w:val="left" /><w:rPr><w:rFonts w:ascii="Times New Roman" w:hAnsi="Times New Roman" w:eastAsia="Times New Roman" w:cs="Times New Roman" /></w:rPr></w:pPr><w:r w:rsidRPr="3DB3F1AF" w:rsidR="3DB3F1AF"><w:rPr><w:rFonts w:ascii="Times New Roman" w:hAnsi="Times New Roman" w:eastAsia="Times New Roman" w:cs="Times New Roman" /></w:rPr><w:t>Contains</w:t></w:r></w:p><w:p w:rsidP="3DB3F1AF" w14:paraId="5316D17B" xmlns:wp14="http://schemas.microsoft.com/office/word/2010/wordml" wp14:textId="4D2E39A6"><w:pPr><w:pStyle w:val="Normal" /><w:numPr><w:ilvl w:val="0" /><w:numId w:val="1" /></w:numPr><w:bidi w:val="0" /><w:jc w:val="left" /><w:rPr><w:rFonts w:ascii="Times New Roman" w:hAnsi="Times New Roman" w:eastAsia="Times New Roman" w:cs="Times New Roman" /></w:rPr></w:pPr><w:r w:rsidRPr="3DB3F1AF" w:rsidR="3DB3F1AF"><w:rPr><w:rFonts w:ascii="Times New Roman" w:hAnsi="Times New Roman" w:eastAsia="Times New Roman" w:cs="Times New Roman" /></w:rPr><w:t>A</w:t></w:r></w:p><w:p w:rsidP="3DB3F1AF" xmlns:wp14="http://schemas.microsoft.com/office/word/2010/wordml" w14:paraId="7F18BFB6" wp14:textId="5E94F574"><w:pPr><w:pStyle w:val="Normal" /><w:numPr><w:ilvl w:val="0" /><w:numId w:val="1" /></w:numPr><w:bidi w:val="0" /><w:jc w:val="left" /><w:rPr><w:rFonts w:ascii="Times New Roman" w:hAnsi="Times New Roman" w:eastAsia="Times New Roman" w:cs="Times New Roman" /></w:rPr></w:pPr><w:r w:rsidRPr="3DB3F1AF" w:rsidR="3DB3F1AF"><w:rPr><w:rFonts w:ascii="Times New Roman" w:hAnsi="Times New Roman" w:eastAsia="Times New Roman" w:cs="Times New Roman" /></w:rPr><w:t>List</w:t></w:r></w:p><w:p w:rsidP="3DB3F1AF" xmlns:wp14="http://schemas.microsoft.com/office/word/2010/wordml" w14:paraId="11744FB4" wp14:textId="1FBE9092"><w:pPr><w:pStyle w:val="Normal" /><w:bidi w:val="0" /><w:ind w:left="0" /><w:jc w:val="left" /><w:rPr><w:rFonts w:ascii="Times New Roman" w:hAnsi="Times New Roman" w:eastAsia="Times New Roman" w:cs="Times New Roman" /></w:rPr></w:pPr></w:p><w:p w:rsidP="3DB3F1AF" w14:paraId="038FA866" xmlns:wp14="http://schemas.microsoft.com/office/word/2010/wordml" wp14:textId="30CC54A8"><w:pPr><w:pStyle w:val="Normal" /><w:bidi w:val="0" /><w:ind w:left="0" /><w:jc w:val="left" /><w:rPr><w:rFonts w:ascii="Times New Roman" w:hAnsi="Times New Roman" w:eastAsia="Times New Roman" w:cs="Times New Roman" /></w:rPr></w:pPr><w:r w:rsidRPr="3DB3F1AF" w:rsidR="753A3357"><w:rPr><w:rFonts w:ascii="Times New Roman" w:hAnsi="Times New Roman" w:eastAsia="Times New Roman" w:cs="Times New Roman" /></w:rPr><w:t xml:space="preserve">It looks </w:t></w:r><w:r w:rsidRPr="3DB3F1AF" w:rsidR="753A3357"><w:rPr><w:rFonts w:ascii="Times New Roman" w:hAnsi="Times New Roman" w:eastAsia="Times New Roman" w:cs="Times New Roman" /></w:rPr><w:t>simple</w:t></w:r><w:r w:rsidRPr="3DB3F1AF" w:rsidR="753A3357"><w:rPr><w:rFonts w:ascii="Times New Roman" w:hAnsi="Times New Roman" w:eastAsia="Times New Roman" w:cs="Times New Roman" /></w:rPr><w:t xml:space="preserve">. </w:t></w:r></w:p><w:sectPr><w:type w:val="nextPage" /><w:pgSz w:w="11906" w:h="16838" w:orient="portrait" /><w:pgMar w:top="1134" w:right="1134" w:bottom="1134" w:left="1134" w:header="0" w:footer="0" w:gutter="0" /><w:pgNumType w:fmt="decimal" /><w:formProt w:val="false" /><w:textDirection w:val="lrTb" /></w:sectPr></w:body></w:document>